pg/__init__.py
pg/_pg.cp312-win_amd64.pyd
pg/_pg.pyi
pg/adapt.py
pg/attrs.py
pg/cast.py
pg/core.py
pg/db.py
pg/error.py
pg/helpers.py
pg/notify.py
pg/py.typed
pg/tz.py
pgdb/__init__.py
pgdb/adapt.py
pgdb/cast.py
pgdb/connect.py
pgdb/connection.py
pgdb/constants.py
pgdb/cursor.py
pgdb/py.typed
pgdb/typecode.py
pygresql-6.2.3.dist-info/licenses/LICENSE.txt
pygresql-6.2.3.dist-info/METADATA
pygresql-6.2.3.dist-info/WHEEL
pygresql-6.2.3.dist-info/top_level.txt
pygresql-6.2.3.dist-info/RECORD
