Metadata-Version: 2.4
Name: PyGreSQL
Version: 6.2.3
Summary: Python PostgreSQL interfaces
Home-page: https://pygresql.github.io/
Download-URL: https://pygresql.github.io/download/
Author: D'Arcy J. M. Cain
Author-email: "D'Arcy J. M. Cain" <darcy@pygresql.org>, Christoph Zwerschke <cito@online.de>
License-Expression: PostgreSQL
Project-URL: Homepage, https://pygresql.github.io/
Project-URL: Documentation, https://pygresql.github.io/contents/
Project-URL: Source Code, https://github.com/PyGreSQL/PyGreSQL
Project-URL: Issue Tracker, https://github.com/PyGreSQL/PyGreSQL/issues/
Project-URL: Changelog, https://pygresql.github.io/contents/changelog.html
Project-URL: Download, https://pygresql.github.io/download/
Project-URL: Mailing List, https://mail.vex.net/mailman/listinfo/pygresql
Keywords: pygresql,postgresql,database,api,dbapi
Classifier: Development Status :: 6 - Mature
Classifier: Intended Audience :: Developers
Classifier: Operating System :: OS Independent
Classifier: Programming Language :: C
Classifier: Programming Language :: Python
Classifier: Programming Language :: Python :: 3
Classifier: Programming Language :: Python :: 3.8
Classifier: Programming Language :: Python :: 3.9
Classifier: Programming Language :: Python :: 3.10
Classifier: Programming Language :: Python :: 3.11
Classifier: Programming Language :: Python :: 3.12
Classifier: Programming Language :: Python :: 3.13
Classifier: Programming Language :: Python :: 3.14
Classifier: Programming Language :: SQL
Classifier: Topic :: Database
Classifier: Topic :: Database :: Front-Ends
Classifier: Topic :: Software Development :: Libraries :: Python Modules
Requires-Python: >=3.8
License-File: LICENSE.txt
Dynamic: author
Dynamic: download-url
Dynamic: home-page
Dynamic: license-file
